mcp_server_bmi_calculator/__init__.py
mcp_server_bmi_calculator/__main__.py
mcp_server_bmi_calculator/server.py
mcp_server_bmi_calculator-0.2.2.dist-info/METADATA
mcp_server_bmi_calculator-0.2.2.dist-info/WHEEL
mcp_server_bmi_calculator-0.2.2.dist-info/entry_points.txt
mcp_server_bmi_calculator-0.2.2.dist-info/RECORD
