Metadata-Version: 2.4
Name: mcp-server-bmi-calculator
Version: 0.2.2
Summary: A Model Context Protocol server for BMI (Body Mass Index) calculation and health assessment
Project-URL: Homepage, https://github.com/yourusername/mcp-server-bmi-calculator
Project-URL: Repository, https://github.com/yourusername/mcp-server-bmi-calculator
Project-URL: Issues, https://github.com/yourusername/mcp-server-bmi-calculator/issues
Author-email: BMI Calculator Team <bmi@example.com>
License: MIT
Keywords: bmi,calculator,health,llm,mcp
Classifier: Development Status :: 4 - Beta
Classifier: Intended Audience :: Developers
Classifier: License :: OSI Approved :: MIT License
Classifier: Programming Language :: Python :: 3
Classifier: Programming Language :: Python :: 3.10
Classifier: Programming Language :: Python :: 3.11
Classifier: Programming Language :: Python :: 3.12
Requires-Python: >=3.10
Requires-Dist: mcp>=1.0.0
Requires-Dist: pydantic>=2.0.0
